tefas/__init__.py
tefas/crawler.py
tefas/schema.py
tests/__init__.py
tests/test_crawler.py
tests/test_data_schema.py
tefas_crawler-0.4.0.dist-info/LICENSE
tefas_crawler-0.4.0.dist-info/METADATA
tefas_crawler-0.4.0.dist-info/WHEEL
tefas_crawler-0.4.0.dist-info/top_level.txt
tefas_crawler-0.4.0.dist-info/RECORD
