Metadata-Version: 2.1
Name: tefas-crawler
Version: 0.4.0
Summary: Crawl the public data from Tefas.
Home-page: https://github.com/burakyilmaz321/tefas-crawler
Download-URL: https://pypi.org/project/tefas-crawler/
Author: Burak Yilmaz
Author-email: burakyilmaz321@gmail.com
License: MIT
Classifier: License :: OSI Approved :: MIT License
Classifier: Programming Language :: Python :: 3.7
Classifier: Programming Language :: Python :: 3.8
Classifier: Programming Language :: Python :: 3.9
Classifier: Programming Language :: Python :: 3.10
Classifier: Programming Language :: Python :: 3.11
Classifier: Development Status :: 5 - Production/Stable
Requires-Python: >=3.7
License-File: LICENSE
Requires-Dist: requests
Requires-Dist: marshmallow
Requires-Dist: pandas
Requires-Dist: urllib3
Provides-Extra: dev
Requires-Dist: pylint ; extra == 'dev'
Requires-Dist: flake8 ; extra == 'dev'
Requires-Dist: black ; extra == 'dev'
Requires-Dist: ipykernel ; extra == 'dev'
Requires-Dist: ipython ; extra == 'dev'
Requires-Dist: jupyter ; extra == 'dev'
Requires-Dist: tox ; extra == 'dev'
Requires-Dist: coverage ; extra == 'dev'
Requires-Dist: pytest-cov ; extra == 'dev'
Requires-Dist: tox-gh-actions ; extra == 'dev'
